HDL/random_ctrl/random.sv
// Code your design here
module latch_rcl (data_out, in, clk);
    input in, clk;
    output data_out;
    reg data_out;

    always @ (clk)
        data_out <= in;
endmodule
module RandomLogic (
    // Outputs
    BRK5, BR2, _ADL_PCL, PC_DB, 
    ADH_ABH, ADL_ABL, Y_SB, X_SB, SB_Y, SB_X, S_SB, S_ADL, SB_S, S_S, 
    NDB_ADD, DB_ADD, Z_ADD, SB_ADD, ADL_ADD, ANDS, EORS, ORS, _ADDC, SRS, SUMS, _DAA, ADD_SB7, ADD_SB06, ADD_ADL, _DSA,
    Z_ADH0, SB_DB, SB_AC, SB_ADH, Z_ADH17, AC_SB, AC_DB, 
    ADH_PCH, PCH_PCH, PCH_DB, PCL_DB, PCH_ADH, PCL_PCL, PCL_ADL, ADL_PCL, DL_ADL, DL_ADH, DL_DB,
    P_DB, ACR_C, AVR_V, DBZ_Z, DB_N, DB_P, DB_C, DB_V, IR5_C, IR5_I, IR5_D, ZERO_V, ONE_V,
    // Inputs
    PHI0, BRK6E, Z_ADL0, SO, RDY, BRFW, ACRL2, _C_OUT, _D_OUT, _ready, T0, T1, T5, T6,
    decoder
);
    output wire BRK5, BR2, _ADL_PCL, PC_DB;
    output wire ADH_ABH, ADL_ABL, Y_SB, X_SB, SB_Y, SB_X, S_SB, S_ADL, SB_S, S_S;
    output wire NDB_ADD, DB_ADD, Z_ADD, SB_ADD, ADL_ADD, ANDS, EORS, ORS, _ADDC, SRS, SUMS, _DAA, ADD_SB7, ADD_SB06, ADD_ADL, _DSA;
    output wire Z_ADH0, SB_DB, SB_AC, SB_ADH, Z_ADH17, AC_SB, AC_DB;
    output wire ADH_PCH, PCH_PCH, PCH_DB, PCL_DB, PCH_ADH, PCL_PCL, PCL_ADL, ADL_PCL, DL_ADL, DL_ADH, DL_DB;
    output wire P_DB, ACR_C, AVR_V, DBZ_Z, DB_N, DB_P, DB_C, DB_V, IR5_C, IR5_I, IR5_D, ZERO_V, ONE_V;
 
    input PHI0, BRK6E, Z_ADL0, SO, RDY, BRFW, ACRL2, _C_OUT, _D_OUT, _ready, T0, T1, T5, T6;
 
    input [129:0] decoder;
 
    // Clocks
    wire PHI1, PHI2;
    assign PHI1 = ~PHI0;
    assign PHI2 = PHI0;
 
    // Temp Wires and Latches (helpers)
    wire NotReadyPhi1, ReadyDelay1_Out, ReadyDelay2_Out;
    wire BR0, BR3, PGX, JSR_5, RTS_5, RTI_5, PushPull, IND, IMPL, _MemOP, JB, STKOP, STOR, STXY, SBXY, STK2, TXS, JSR2, SBC0;
    wire ROR, _SRS, _ANDS, _EORS, _ORS, NOADL, BRX, RET, INC_SB, CSET, STA, JSXY, _ZTST, ABS_2, JMP_4;
    latch_rcl NotReadyPhi1_Latch ( NotReadyPhi1, _ready, PHI1 );
    assign PGX = ~(decoder[71] | decoder[72]) & ~BR0;
    latch_rcl ReadyDelay1 ( ReadyDelay1_Out, ~RDY, PHI2 );
    latch_rcl ReadyDelay2 ( ReadyDelay2_Out, ~ReadyDelay1_Out, PHI1 );
    assign BR0 = ~(~ReadyDelay2_Out | decoder[73]);
    assign BR2 = decoder[80];
    assign BR3 = decoder[93];
    assign JSR_5 = decoder[56];
    assign RTS_5 = decoder[84];
    assign RTI_5 = decoder[26];
    assign BRK5 = decoder[22];
    assign PushPull = decoder[129];
    assign STK2 = decoder[35];
    assign TXS = decoder[13];
    assign JSR2 = decoder[48];
    assign SBC0 = decoder[51];
    assign ROR = decoder[27];
    assign RET = decoder[47];
    assign STA = decoder[79];
    assign JMP_4 = decoder[102];
    assign IND = ( decoder[89] | ~(PushPull | decoder[90]) | decoder[91] | RTS_5 );
    assign IMPL = decoder[128] & ~PushPull;
    assign _MemOP = ~( decoder[111] | decoder[122] | decoder[123] | decoder[124] | decoder[125] );
    assign JB = ~( decoder[94] | decoder[95] | decoder[96] );
    assign STKOP = ~( NotReadyPhi1 | ~(decoder[21] | BRK5 | decoder[23] | decoder[24] | decoder[25] | RTI_5) );
    assign STOR = ~( ~decoder[97] | _MemOP );
    assign STXY = ~(STOR & decoder[0]) & ~(STOR & decoder[12]);
    assign SBXY = ~(_SB_X & _SB_Y);
    assign _SRS = ~(~(decoder[76] & T5) & ~decoder[75]);
    assign _ANDS = decoder[69] | decoder[70];
    assign _EORS = decoder[29];
    assign _ORS = _ready | decoder[32];
    assign NOADL = ~( decoder[85] | decoder[86] | RTS_5 | RTI_5 | decoder[87] | decoder[88] | decoder[89] );
    assign BRX = decoder[49] | decoder[50] | ~(~BR3 | BRFW);
    assign INC_SB = ~(~(decoder[39] | decoder[40] | decoder[41] | decoder[42] | decoder[43]) & ~(decoder[44] & T5));
    assign CSET = ~( ( ( ~(T0 | T5) | _C_OUT) | ~(decoder[52] | decoder[53])) & ~decoder[54]);
    assign JSXY = ~(~JSR2 & STXY);
    assign _ZTST = ~( ~_SB_AC | SBXY | T6 | _ANDS );
    assign ABS_2 = ~( decoder[83] | PushPull);
 
    // XYS Regs Control
    wire YSB_Out, XSB_Out, _SB_X, _SB_Y, SBY_Out, SBX_Out, SSB_Out, SADL_Out, _SB_S, SBS_Out, SS_Out;
    latch_rcl YSB ( YSB_Out, 
        (~(STOR & decoder[0])) & (~(decoder[1]|decoder[2]|decoder[3]|decoder[4]|decoder[5])) & (~(decoder[6] & decoder[7])),
        PHI2 );
    latch_rcl XSB ( XSB_Out,
        (~(decoder[6] & ~decoder[7])) & (~(decoder[8]|decoder[9]|decoder[10]|decoder[11]|TXS)) & (~(STOR & decoder[12])),
        PHI2 );
    assign Y_SB = ~YSB_Out & ~PHI2;
    assign X_SB = ~XSB_Out & ~PHI2;
    assign _SB_X = ~(decoder[14] | decoder[15] | decoder[16]);
    assign _SB_Y = ~(decoder[18] | decoder[19] | decoder[20]);
    latch_rcl SBY ( SBY_Out, _SB_Y, PHI2 );
    assign SB_Y = ~SBY_Out & ~PHI2;
    latch_rcl SBX ( SBX_Out, _SB_X, PHI2 );
    assign SB_X = ~SBX_Out & ~PHI2;
    latch_rcl SSB ( SSB_Out, ~decoder[17], PHI2 );
    assign S_SB = ~SSB_Out;
    latch_rcl SADL ( SADL_Out, ~(decoder[21] & ~NotReadyPhi1) & ~STK2, PHI2 );
    assign S_ADL = ~SADL_Out;
    assign _SB_S = ~( STKOP | ~(~JSR2 | NotReadyPhi1) | TXS );
    latch_rcl SBS ( SBS_Out, _SB_S, PHI2 );
    assign SB_S = ~SBS_Out & ~PHI2;
    latch_rcl SS ( SS_Out, ~_SB_S, PHI2 );
    assign S_S = ~SS_Out & ~PHI2;
 
    // ALU Control
    wire _NDB_ADD, _ADL_ADD, SB_ADD_Int, NDBADD_Out, DBADD_Out, ZADD_Out, SBADD_Out, ADLADD_Out;
    assign _NDB_ADD = ~( BRX | SBC0 | JSR_5) | _ready;
    assign _ADL_ADD = ~(decoder[33] & ~decoder[34]) & ~( STK2 | decoder[36] | decoder[37] | decoder[38] | decoder[39] | _ready );
    assign SB_ADD_Int = ~( decoder[30] | decoder[31] | RET | _ready | STKOP | INC_SB | decoder[45] | BRK6E | JSR2 );
    latch_rcl NDBADD (NDBADD_Out, _NDB_ADD, PHI2 );
    assign NDB_ADD = ~NDBADD_Out & ~PHI2;
    latch_rcl DBADD (DBADD_Out, ~(_NDB_ADD & _ADL_ADD), PHI2 );
    assign DB_ADD = ~DBADD_Out & ~PHI2;
    latch_rcl ZADD (ZADD_Out, SB_ADD_Int, PHI2 );
    assign Z_ADD = ~ZADD_Out & ~PHI2;
    latch_rcl SBADD (SBADD_Out, ~SB_ADD_Int, PHI2);
    assign SB_ADD = ~SBADD_Out & ~PHI2;
    latch_rcl ADLADD ( ADLADD_Out, _ADL_ADD, PHI2 );
    assign ADL_ADD = ~ADLADD_Out & ~PHI2;
    wire ANDS1_Out, ANDS2_Out, EORS1_Out, EORS2_Out, ORS1_Out, ORS2_Out, SRS1_Out, SRS2_Out, SUMS1_Out, SUMS2_Out;
    latch_rcl ANDS1 ( ANDS1_Out, _ANDS, PHI2 );
    latch_rcl ANDS2 ( ANDS2_Out, ~ANDS1_Out, PHI1 );
    assign ANDS = ~ANDS2_Out;
    latch_rcl EORS1 ( EORS1_Out, _EORS, PHI2 );
    latch_rcl EORS2 ( EORS2_Out, ~EORS1_Out, PHI1 );
    assign EORS = ~EORS2_Out;
    latch_rcl ORS1 ( ORS1_Out, _ORS, PHI2 );
    latch_rcl ORS2 ( ORS2_Out, ~ORS1_Out, PHI1 );
    assign ORS = ~ORS2_Out;
    latch_rcl SRS1 ( SRS1_Out, _SRS, PHI2 );
    latch_rcl SRS2 ( SRS2_Out, ~SRS1_Out, PHI1 );
    assign SRS = ~SRS2_Out;
    latch_rcl SUMS1 ( SUMS1_Out, ~( _ANDS | _EORS | _ORS | _SRS ), PHI2 );
    latch_rcl SUMS2 ( SUMS2_Out, ~SUMS1_Out, PHI1 );
    assign SUMS = ~SUMS2_Out;
    wire [6:0] ADDSB7_Out;
    wire _ADD_SB7, _ADD_SB06, ADD_SB7_Out, ADD_SB06_Out;
    latch_rcl ADDSB7_1 ( ADDSB7_Out[1], ~_C_OUT, PHI2 );
    latch_rcl ADDSB7_2 ( ADDSB7_Out[2], ~(NotReadyPhi1 | ~_SRS), PHI2 );
    latch_rcl ADDSB7_3 ( ADDSB7_Out[3], _SRS, PHI2 );
    latch_rcl ADDSB7_4 ( ADDSB7_Out[4], ~ADDSB7_Out[3], PHI1 );
    latch_rcl ADDSB7_5 ( ADDSB7_Out[5], ~(~ADDSB7_Out[1] & ADDSB7_Out[2]) & ~(~ADDSB7_Out[2] & ADDSB7_Out[6]), PHI1 );
    latch_rcl ADDSB7_6 ( ADDSB7_Out[6], ~ADDSB7_Out[5], PHI2 );
    assign _ADD_SB7 = ~( ~ADDSB7_Out[4] | ~ROR | ~ADDSB7_Out[5] );
    assign _ADD_SB06 = ~( T6 | STKOP | PGX | T1 | JSR_5 );
    latch_rcl ADD_SB7Latch ( ADD_SB7_Out, ~(_ADD_SB7 | _ADD_SB06), PHI2 );
    assign ADD_SB7 = ~ADD_SB7_Out;
    latch_rcl ADD_SB06Latch ( ADD_SB06_Out, _ADD_SB06, PHI2 );
    assign ADD_SB06 = ~ADD_SB06_Out;
    wire ADDADL_Out;
    latch_rcl ADDADL ( ADDADL_Out, PGX | NOADL, PHI2 );
    assign ADD_ADL = ~ADDADL_Out;
    wire DSA1_Out, DSA2_Out, DAA1_Out, DAA2_Out;
    latch_rcl DSA1 ( DSA1_Out, SBC0 | ~(decoder[52] & ~_D_OUT), PHI2 );
    latch_rcl DSA2 ( DSA2_Out, ~DSA1_Out, PHI1 );
    assign _DSA = ~DSA2_Out;
    latch_rcl DAA1 ( DAA1_Out, ~(SBC0 & ~_D_OUT), PHI2 );
    latch_rcl DAA2 ( DAA2_Out, ~DAA1_Out, PHI1 );
    assign _DAA = ~DAA2_Out;
    wire ACIN1_Out, ACIN2_Out, ACIN3_Out, ACIN4_Out, _ACIN_Int;
    latch_rcl ACIN1 ( ACIN1_Out, ~(~RET | _ADL_ADD), PHI2 );
    latch_rcl ACIN2 ( ACIN2_Out, INC_SB, PHI2 );
    latch_rcl ACIN3 ( ACIN3_Out, BRX, PHI2 );
    latch_rcl ACIN4 ( ACIN4_Out, CSET, PHI2 );
    assign _ACIN_Int = ~(ACIN1_Out | ACIN2_Out | ACIN3_Out | ACIN4_Out);
    latch_rcl ACIN ( _ADDC, _ACIN_Int, PHI1 );
    wire _SB_AC, _AC_SB, _AC_DB, SBAC_Out, ACSB_Out, ACDB_Out;
    assign _SB_AC = ~( decoder[58] | decoder[59] | decoder[60] | decoder[61] | decoder[62] | decoder[63] | decoder[64] );
    latch_rcl SBAC ( SBAC_Out, _SB_AC, PHI2 );
    assign SB_AC = ~SBAC_Out & ~PHI2;
    assign _AC_SB = (~(decoder[65] & ~decoder[64])) & ~( decoder[66] | decoder[67] | decoder[68] | _ANDS);
    latch_rcl ACSB ( ACSB_Out, _AC_SB, PHI2 );
    assign AC_SB = ~ACSB_Out & ~PHI2;
    assign _AC_DB = ~(STA & STOR) & ~decoder[74];
    latch_rcl ACDB ( ACDB_Out, _AC_DB, PHI2 );
    assign AC_DB = ~ACDB_Out & ~PHI2;
    
    // SB/DB Control
    wire _SB_ADH, _SB_DB, SBADH_Out, SBDB_Out;
    assign _SB_ADH = ~(PGX | BR3);
    latch_rcl SBADH ( SBADH_Out, _SB_ADH, PHI2 );
    assign SB_ADH = ~SBADH_Out;
    assign _SB_DB = ~( ~(_ZTST | _ANDS) | decoder[67] | (decoder[55] & T5) | T1 | BR2 | JSXY);
    latch_rcl SBDB ( SBDB_Out, _SB_DB, PHI2 );
    assign SB_DB = ~SBDB_Out;

    // PCH/PCL Control
    wire _ADH_PCH, _PCH_DB, _PCL_DB, ADHPCH_Out, PCHPCH_Out, PCHDB_Out, PCLDB1_Out, PCLDB2_Out, PCLDB_Out;
    assign _ADH_PCH = ~( RTS_5 | ABS_2 | BR3 | T1 | BR2 | T0 );
    latch_rcl ADHPCH ( ADHPCH_Out, _ADH_PCH, PHI2 );
    assign ADH_PCH = ~ADHPCH_Out & ~PHI2;
    latch_rcl PCHPCH ( PCHPCH_Out, ~_ADH_PCH, PHI2 );
    assign PCH_PCH = ~PCHPCH_Out & ~PHI2;
    assign _PCH_DB = ~( decoder[77] | decoder[78] );
    latch_rcl PCHDB ( PCHDB_Out, _PCH_DB, PHI2 );
    assign PCH_DB = ~PCHDB_Out;
    latch_rcl PCLDB1 ( PCLDB1_Out, _PCH_DB, PHI2 );
    latch_rcl PCLDB2 ( PCLDB2_Out, ~( PCLDB1_Out | _ready), PHI1 );
    assign _PCL_DB = PCLDB2_Out;
    latch_rcl PCLDB ( PCLDB_Out, _PCL_DB, PHI2 );
    assign PCL_DB = ~PCLDB_Out;
    assign PC_DB = ~(_PCH_DB & _PCL_DB);
    wire _PCH_ADH, _PCL_ADL, PCHADH_Out, PCLPCL_Out, ADLPCL_Out, PCLADL_Out;
    assign _PCH_ADH = ~( ~(_PCL_ADL | BR0 | DL_PCH) | BR3);
    latch_rcl PCHADH ( PCHADH_Out, _PCH_ADH, PHI2 );
    assign _PCL_ADL = ~( ABS_2 | T1 | BR2 | JSR_5 | ~( ~(JB | NotReadyPhi1) | ~T0));
    assign _ADL_PCL = ~(~_PCL_ADL | T0 | RTS_5) & ~(BR3 & ~NotReadyPhi1);
    latch_rcl PCLCPL ( PCLPCL_Out, ~_ADL_PCL, PHI2);
    assign PCL_PCL = ~PCLPCL_Out & ~PHI2;
    latch_rcl PCLADL ( PCLADL_Out, _PCL_ADL, PHI2 );
    assign PCL_ADL = ~PCLADL_Out;
    latch_rcl ADLPCL ( ADLPCL_Out, _ADL_PCL, PHI2 );
    assign ADL_PCL = ~ADLPCL_Out & ~PHI2;
 
    // DL Control
    wire _DL_ADL, DL_PCH, DLADL_Out, DLADH_Out, DLDB_Out;
    assign _DL_ADL = ~(decoder[81] | decoder[82]);
    latch_rcl DLADL ( DLADL_Out, _DL_ADL, PHI2 );
    assign DL_ADL = ~DLADL_Out;
    assign DL_PCH = ~( ~T0 | JB);
    latch_rcl DLADH ( DLADH_Out, ~(DL_PCH | IND), PHI2 );
    assign DL_ADH = ~DLADH_Out;
    latch_rcl DLDB ( DLDB_Out, ~( JMP_4 | T5 | INC_SB | BRK6E | JSR2 | decoder[45] | decoder[46] | RET | ~(~(ABS_2 | T0) | IMPL) | BR2 ), PHI2 );
    assign DL_DB = ~DLDB_Out;

    // ADH/ADL Control
    wire _Z_ADH17, _ADL_ABL, ADHABH_Out, ADLABL_Out, ZADH0_Out, ZADH17_Out;
    latch_rcl ADHABH ( ADHABH_Out, 
        ( ~(~( ~(T2 | _PCH_PCH | JSR_5 | IND) | _ready) | ~(~(~NotReadyPhi1 & ACRL2) | _SB_ADH)) | BR3) & ~Z_ADL0,
        PHI2 );
    assign ADH_ABH = ~ADHABH_Out;
    assign _ADL_ABL = ~(~((decoder[71] | decoder[72]) | _ready) & ~(T5 | T6));
    latch_rcl ADLABL ( ADLABL_Out, _ADL_ABL, PHI2 );
    assign ADL_ABL = ~ADLABL_Out;
    latch_rcl ZADH0 ( ZADH0_Out, _DL_ADL, PHI2 );
    assign Z_ADH0 = ~ZADH0_Out;
    assign _Z_ADH17 = ~(decoder[57] | ~_DL_ADL);
    latch_rcl ZADH17 ( ZADH17_Out, _Z_ADH17, PHI2 );
    assign Z_ADH17 = ~ZADH17_Out;
 
    // Flags Control
    wire PDB_Out, ACRC_Out, DBZZ_Out, PIN_Out, BIT1_Out, DBC_Out, DBV_Out, IR5C_Out, IR5I_Out, IR5D_Out, ZEROV_Out;
    wire SODelay1_Out, SODelay2_Out, SODelay3_Out;
    latch_rcl PDB ( PDB_Out, ~(decoder[98] | decoder[99]), PHI2 );
    assign P_DB = ~PDB_Out;
    latch_rcl ACRC ( ACRC_Out, ~(decoder[112] | decoder[116] | decoder[117] | decoder[118] | decoder[119]) & ~(decoder[107] & T6), PHI2 );
    assign ACR_C = ~ACRC_Out;
    latch_rcl AVRV ( AVR_V, decoder[112], PHI2 );
    latch_rcl DBZZ ( DBZZ_Out, ~(ACR_C | decoder[109] | ~_ZTST), PHI2 );
    assign DBZ_Z = ~DBZZ_Out;
    latch_rcl PIN ( PIN_Out, ~(decoder[114] | decoder[115]), PHI2 );
    latch_rcl BIT1 ( BIT1_Out, decoder[109], PHI2 );
    assign DB_N = ~(PIN_Out & DBZZ_Out) & ~BIT1_Out;
    assign DB_P = PIN_Out & ~_ready;
    latch_rcl DBC ( DBC_Out, ~(_SRS | DB_P), PHI2 );
    assign DB_C = ~DBC_Out;
    latch_rcl DBV ( DBV_Out, ~decoder[113], PHI2 );
    assign DB_V = ~(DBV_Out & PIN_Out);
    latch_rcl IR5C ( IR5C_Out, ~decoder[110], PHI2 );
    assign IR5_C = ~IR5C_Out;
    latch_rcl IR5I ( IR5I_Out, ~decoder[108], PHI2 );
    assign IR5_I = ~IR5I_Out;
    latch_rcl IR5D ( IR5D_Out, ~decoder[120], PHI2 );
    assign IR5_D = ~IR5D_Out;
    latch_rcl ZEROV ( ZEROV_Out, ~decoder[127], PHI2 );
    assign ZERO_V = ~ZEROV_Out;
    latch_rcl SODelay1 ( SODelay1_Out, ~SO, PHI1 );
    latch_rcl SODelay2 ( SODelay2_Out, ~SODelay1_Out, PHI2 );
    latch_rcl SODelay3 ( SODelay3_Out, ~SODelay2_Out, PHI1 );
    latch_rcl ONEV ( ONE_V, ~(SODelay3_Out | ~SODelay1_Out), PHI2 );
 
endmodule   // RandomLogic

HDL/random_ctrl/testbench.sv
module testbench;
  
  reg PHI0, BRK6E, Z_ADL0, SO, RDY, BRFW, ACRL2, _C_OUT, _D_OUT, _ready, T0, T1, T5, T6;
  reg [129:0] decoder;
  
  wire BRK5, BR2, _ADL_PCL, PC_DB, 
    ADH_ABH, ADL_ABL, Y_SB, X_SB, SB_Y, SB_X, S_SB, S_ADL, SB_S, S_S, 
    NDB_ADD, DB_ADD, Z_ADD, SB_ADD, ADL_ADD, ANDS, EORS, ORS, _ADDC, SRS, SUMS, _DAA, ADD_SB7, ADD_SB06, ADD_ADL, _DSA,
    Z_ADH0, SB_DB, SB_AC, SB_ADH, Z_ADH17, AC_SB, AC_DB, 
    ADH_PCH, PCH_PCH, PCH_DB, PCL_DB, PCH_ADH, PCL_PCL, PCL_ADL, ADL_PCL, DL_ADL, DL_ADH, DL_DB,
    P_DB, ACR_C, AVR_V, DBZ_Z, DB_N, DB_P, DB_C, DB_V, IR5_C, IR5_I, IR5_D, ZERO_V, ONE_V;
  
  RandomLogic random(
    .BRK5(BRK5),
    .BR2(BR2), 
    ._ADL_PCL(_ADL_PCL), 
    .PC_DB(PC_DB), 
    .ADH_ABH(ADH_ABH), 
    .ADL_ABL(ADL_ABL), 
    .Y_SB(Y_SB),
    .X_SB(X_SB), 
    .SB_Y(SB_Y), 
    .SB_X(SB_X), 
    .S_SB(S_SB), 
    .S_ADL(S_ADL), 
    .SB_S(SB_S), 
    .S_S(S_S), 
    .NDB_ADD(NDB_ADD), 
    .DB_ADD(DB_ADD), 
    .Z_ADD(Z_ADD), 
    .SB_ADD(SB_ADD), 
    .ADL_ADD(ADL_ADD), 
    .ANDS(ANDS), 
    .EORS(EORS), 
    .ORS(ORS), 
    ._ADDC(_ADDC), 
    .SRS(SRS), 
    .SUMS(SUMS), 
    ._DAA(_DAA), 
    .ADD_SB7(ADD_SB7), 
    .ADD_SB06(ADD_SB06), 
    .ADD_ADL(ADD_ADL), 
    ._DSA(_DSA),
    .Z_ADH0(Z_ADH0), 
    .SB_DB(SB_DB), 
    .SB_AC(SB_AC), 
    .SB_ADH(SB_ADH), 
    .Z_ADH17(Z_ADH17), 
    .AC_SB(AC_SB), 
    .AC_DB(AC_DB), 
    .ADH_PCH(ADH_PCH),
    .PCH_PCH(PCH_PCH), 
    .PCH_DB(PCH_DB), 
    .PCL_DB(PCL_DB), 
    .PCH_ADH(PCH_ADH), 
    .PCL_PCL(PCL_PCL), 
    .PCL_ADL(PCL_ADL), 
    .ADL_PCL(ADL_PCL), 
    .DL_ADL(DL_ADL), 
    .DL_ADH(DL_ADH), 
    .DL_DB(DL_DB),
    .P_DB(P_DB), 
    .ACR_C(ACR_C), 
    .AVR_V(AVR_V), 
    .DBZ_Z(DBZ_Z), 
    .DB_N(DB_N), 
    .DB_P(DB_P), 
    .DB_C(DB_C), 
    .DB_V(DB_V), 
    .IR5_C(IR5_C), 
    .IR5_I(IR5_I),
    .IR5_D(IR5_D), 
    .ZERO_V(ZERO_V), 
    .ONE_V(ONE_V),
    .PHI0(PHI0),
    .BRK6E(BRK6E), 
    .Z_ADL0(Z_ADL0), 
    .SO(SO), 
    .RDY(RDY), 
    .BRFW(BRFW), 
    .ACRL2(ACRL2),
    ._C_OUT(_C_OUT), 
    ._D_OUT(_D_OUT), 
    ._ready(_ready), 
    .T0(T0), 
    .T1(T1),
    .T5(T5), 
    .T6(T6),
    .decoder(decoder)
  );

  initial begin
    $dumpfile("dump.vcd");
    $dumpvars(1, testbench);
    
    PHI0 = 1'b0;
    #50;
    
	//decoder = 0 << 128 +  9511602414080229376 << 64 +  0
	//decoder = 0 << 128 +  4755801207576985600 << 64 +  0;
	decoder = 0;

    PHI0   = 0;
    BRK6E  = 0;
    Z_ADL0 = 0;
    SO     = 0;
    RDY    = 1;
    BRFW   = 1;
    ACRL2  = 0;
    _C_OUT = 1;
    _D_OUT = 1;
    _ready = 0;
    T0 = 1;
    T1 = 0;
    T5 = 1;
    T6 = 0;
    
    #50;

	$display("DL_DB: ", DL_DB);
	$display("DL_ADL: ", DL_ADL);
	$display("DL_ADH: ", DL_ADH);
	$display("Z_ADH0: ", Z_ADH0);
	$display("Z_ADH17: ", Z_ADH17);
	$display("ADH_ABH: ", ADH_ABH);
	$display("ADL_ABL: ", ADL_ABL);
	$display("PCL_PCL: ", PCL_PCL);
	$display("ADL_PCL: ", ADL_PCL);

    $finish;
  end
endmodule

HDL/random_ctrl/dump.vcd
$date
	Thu Sep 23 19:25:20 2021
$end
$version
	Icarus Verilog
$end
$timescale
	1s
$end
$scope module testbench $end
$var wire 1 ! PCH_ADH $end
$var wire 1 " _DSA $end
$var wire 1 # _DAA $end
$var wire 1 $ _ADL_PCL $end
$var wire 1 % _ADDC $end
$var wire 1 & Z_ADH17 $end
$var wire 1 ' Z_ADH0 $end
$var wire 1 ( Z_ADD $end
$var wire 1 ) ZERO_V $end
$var wire 1 * Y_SB $end
$var wire 1 + X_SB $end
$var wire 1 , S_SB $end
$var wire 1 - S_S $end
$var wire 1 . S_ADL $end
$var wire 1 / SUMS $end
$var wire 1 0 SRS $end
$var wire 1 1 SB_Y $end
$var wire 1 2 SB_X $end
$var wire 1 3 SB_S $end
$var wire 1 4 SB_DB $end
$var wire 1 5 SB_ADH $end
$var wire 1 6 SB_ADD $end
$var wire 1 7 SB_AC $end
$var wire 1 8 P_DB $end
$var wire 1 9 PC_DB $end
$var wire 1 : PCL_PCL $end
$var wire 1 ; PCL_DB $end
$var wire 1 < PCL_ADL $end
$var wire 1 = PCH_PCH $end
$var wire 1 > PCH_DB $end
$var wire 1 ? ORS $end
$var wire 1 @ ONE_V $end
$var wire 1 A NDB_ADD $end
$var wire 1 B IR5_I $end
$var wire 1 C IR5_D $end
$var wire 1 D IR5_C $end
$var wire 1 E EORS $end
$var wire 1 F DL_DB $end
$var wire 1 G DL_ADL $end
$var wire 1 H DL_ADH $end
$var wire 1 I DB_V $end
$var wire 1 J DB_P $end
$var wire 1 K DB_N $end
$var wire 1 L DB_C $end
$var wire 1 M DB_ADD $end
$var wire 1 N DBZ_Z $end
$var wire 1 O BRK5 $end
$var wire 1 P BR2 $end
$var wire 1 Q AVR_V $end
$var wire 1 R ANDS $end
$var wire 1 S ADL_PCL $end
$var wire 1 T ADL_ADD $end
$var wire 1 U ADL_ABL $end
$var wire 1 V ADH_PCH $end
$var wire 1 W ADH_ABH $end
$var wire 1 X ADD_SB7 $end
$var wire 1 Y ADD_SB06 $end
$var wire 1 Z ADD_ADL $end
$var wire 1 [ AC_SB $end
$var wire 1 \ AC_DB $end
$var wire 1 ] ACR_C $end
$var reg 1 ^ ACRL2 $end
$var reg 1 _ BRFW $end
$var reg 1 ` BRK6E $end
$var reg 1 a PHI0 $end
$var reg 1 b RDY $end
$var reg 1 c SO $end
$var reg 1 d T0 $end
$var reg 1 e T1 $end
$var reg 1 f T5 $end
$var reg 1 g T6 $end
$var reg 1 h Z_ADL0 $end
$var reg 1 i _C_OUT $end
$var reg 1 j _D_OUT $end
$var reg 1 k _ready $end
$var reg 130 l decoder [129:0] $end
$upscope $end
$enddefinitions $end
#0
$dumpvars
b100100000000000000000000000000000000000000000000000000010000000000000000000000000000000000000100000000 l
0k
1j
1i
0h
0g
0f
0e
0d
0c
1b
0a
0`
1_
0^
x]
x\
x[
xZ
xY
xX
xW
xV
xU
xT
xS
xR
xQ
0P
0O
xN
xM
xL
xK
xJ
xI
xH
xG
xF
xE
xD
xC
xB
xA
x@
x?
x>
x=
x<
x;
x:
x9
x8
x7
x6
x5
x4
x3
x2
x1
x0
x/
x.
x-
x,
x+
x*
x)
x(
x'
x&
x%
0$
x#
x"
z!
$end
#10
0I
0,
0.
0Z
04
0>
1<
0G
1H
1F
1W
1U
0'
0&
18
0]
1J
0D
0B
0C
0)
0Q
0*
0+
01
02
03
0-
0A
0M
0(
06
0T
07
0[
0\
0V
0=
0:
0S
1a
#15
19
1#
1"
1/
00
0?
0E
0R
1%
1+
1-
1M
16
1V
1S
0a
#20
0K
1L
0N
1;
05
0Y
1X
0@
0+
0-
0M
06
0V
0S
1a
#25
1+
1-
1M
16
1V
1S
0a
#30
0+
0-
0M
06
0V
0S
1a
#35
1+
1-
1M
16
1V
1S
0a
#40
0+
0-
0M
06
0V
0S
1a
#45
1+
1-
1M
16
1V
1S
0a
